obj2xgl/__init__.py
obj2xgl/__main__.py
obj2xgl/parser.py
obj2xgl/generators/__init__.py
obj2xgl/generators/generator.py
obj2xgl/generators/nds.py
obj2xgl/generators/opengl.py
obj2xgl-0.1.dist-info/METADATA
obj2xgl-0.1.dist-info/WHEEL
obj2xgl-0.1.dist-info/entry_points.txt
obj2xgl-0.1.dist-info/top_level.txt
obj2xgl-0.1.dist-info/RECORD
