Metadata-Version: 2.1
Name: obj2xgl
Version: 0.1
Summary: Convert Wavefront 3D models into C code (OpenGL, NDS, Wii)
Home-page: https://gitlab.com/mardy/obj2xgl
Author: Alberto Mardegan
Author-email: info@mardy.it
Classifier: Development Status :: 3 - Alpha
Classifier: Environment :: Console
Classifier: Intended Audience :: Developers
Classifier: License :: OSI Approved :: MIT License
Classifier: Programming Language :: C
Classifier: Programming Language :: C++
Classifier: Programming Language :: Python :: 3
Classifier: Topic :: Multimedia :: Graphics :: 3D Rendering
Classifier: Topic :: Software Development
Classifier: Topic :: Software Development :: Code Generators
Classifier: Topic :: Utilities
